jpush/__init__.py
jpush/common.py
jpush/core.py
jpush/device/__init__.py
jpush/device/core.py
jpush/device/entity.py
jpush/push/__init__.py
jpush/push/audience.py
jpush/push/core.py
jpush/push/payload.py
jpush/report/__init__.py
jpush/report/core.py
jpush/schedule/__init__.py
jpush/schedule/core.py
jpush/schedule/schedulepayload.py
jpush-3.3.9.dist-info/METADATA
jpush-3.3.9.dist-info/WHEEL
jpush-3.3.9.dist-info/top_level.txt
jpush-3.3.9.dist-info/RECORD
