Metadata-Version: 2.1
Name: jpush
Version: 3.3.9
Summary: JPush's officially supported Python client library
Home-page: https://github.com/jpush/jpush-api-python-client
Author: jpush
Author-email: support@jpush.cn
License: MIT License
Keywords: JPush,JPush API,Android Push,iOS Push
Platform: any
Classifier: Environment :: Console
Classifier: Intended Audience :: Developers
Classifier: License :: OSI Approved :: MIT License
Classifier: Operating System :: OS Independent
Classifier: Programming Language :: Python
Requires-Dist: requests (>=1.2)
